eml2pdf/__init__.py
eml2pdf/eml2pdf.py
eml2pdf/security.py
eml2pdf-0.1.dist-info/LICENSE
eml2pdf-0.1.dist-info/METADATA
eml2pdf-0.1.dist-info/WHEEL
eml2pdf-0.1.dist-info/entry_points.txt
eml2pdf-0.1.dist-info/top_level.txt
eml2pdf-0.1.dist-info/RECORD
