Metadata-Version: 2.2
Name: eml2pdf
Version: 0.1
Summary: Convert .eml (email) files to PDF using Python.
Author-email: Pieter Lenaerts <pieter.lenaerts@outlook.be>, Daniel Grossfeld <github@klokie.com>
Project-URL: Homepage, https://github.com/plenaerts/eml2pdf
Project-URL: Repository, https://github.com/plenaerts/eml2pdf
Project-URL: Issues, https://github.com/plenaerts/eml2pdf/issues
Keywords: eml,pdf,pdf-converter,weasyprint,html,mime,multipart
Classifier: Programming Language :: Python :: 3
Classifier: Operating System :: OS Independent
Requires-Python: >=3.11
License-File: LICENSE
Requires-Dist: weasyprint~=64.0
Requires-Dist: markdown~=3.7
Requires-Dist: hurry.filesize~=0.9
Requires-Dist: beautifulsoup4~=4.13
